{
  "type": "minecraft:crafting_shapeless",
  "category": "misc",
  "ingredients": [
    {
      "tag": "c:nuggets/nickel"
    },
    {
      "tag": "c:nuggets/nickel"
    },
    {
      "tag": "c:nuggets/nickel"
    },
    {
      "tag": "c:nuggets/nickel"
    },
    {
      "tag": "c:nuggets/nickel"
    },
    {
      "tag": "c:nuggets/nickel"
    },
    {
      "tag": "c:nuggets/nickel"
    },
    {
      "tag": "c:nuggets/nickel"
    },
    {
      "tag": "c:nuggets/nickel"
    }
  ],
  "result": {
    "item": "assortedcore:nickel_ingot"
  }
}