{
  "type": "minecraft:crafting_shapeless",
  "ingredients": [
    {
      "item": "assortedcore:bronze_ingot"
    },
    {
      "item": "assortedcore:bronze_ingot"
    },
    {
      "item": "assortedcore:bronze_ingot"
    },
    {
      "item": "assortedcore:bronze_ingot"
    },
    {
      "item": "assortedcore:bronze_ingot"
    },
    {
      "item": "assortedcore:bronze_ingot"
    },
    {
      "item": "assortedcore:bronze_ingot"
    },
    {
      "item": "assortedcore:bronze_ingot"
    },
    {
      "item": "assortedcore:bronze_ingot"
    }
  ],
  "result": {
    "item": "assortedcore:bronze_block"
  }
}